storylinez/__init__.py
storylinez/base_client.py
storylinez/brand.py
storylinez/client.py
storylinez/company_details.py
storylinez/pipeline.py
storylinez/project.py
storylinez/prompt.py
storylinez/render.py
storylinez/search.py
storylinez/sequence.py
storylinez/settings.py
storylinez/stock.py
storylinez/storage.py
storylinez/storyboard.py
storylinez/tools.py
storylinez/user.py
storylinez/utils.py
storylinez/voiceover.py
storylinez-0.3.1b2.dist-info/LICENSE.rst
storylinez-0.3.1b2.dist-info/METADATA
storylinez-0.3.1b2.dist-info/WHEEL
storylinez-0.3.1b2.dist-info/top_level.txt
storylinez-0.3.1b2.dist-info/RECORD
