Metadata-Version: 2.1
Name: storylinez
Version: 0.3.1b2
Summary: Storylinez: A modular library for narrative generation and story manipulation
Home-page: https://github.com/Kawai-Senpai/Storylinez-SDK
Author: Sayanti Chatterjee, Ranit Bhowmick
Author-email: sayantichatterjee28@gmail.com, bhowmickranitking@gmail.com
License: MIT
Requires-Python: >=3.6
License-File: LICENSE.rst
Requires-Dist: python-dotenv
Requires-Dist: ultraprint>=3.3.0
